patoso/__init__.py
patoso/constants.py
patoso/patoso.py
patoso/report.py
patoso/tpfplotter.py
patoso/resources/images/patoso.png
"patoso/tests/TIC25155310_[1,_2]lc.csv"
"patoso/tests/TIC25155310_[1,_2]params_star.csv"
patoso/tests/__init__.py
patoso/tests/test_patoso.py
"patoso/tests/TIC25155310_[1,_2]/Periodogram_Final_TIC25155310_1.png"
"patoso/tests/TIC25155310_[1,_2]/Periodogram_Final_TIC25155310_[1, 2].png"
"patoso/tests/TIC25155310_[1,_2]/Periodogram_Initial_TIC25155310_1.png"
"patoso/tests/TIC25155310_[1,_2]/Periodogram_Initial_TIC25155310_[1, 2].png"
"patoso/tests/TIC25155310_[1,_2]/TIC25155310_[1, 2]_candidates.log"
"patoso/tests/TIC25155310_[1,_2]/TIC25155310_[1, 2]_report.log"
"patoso/tests/TIC25155310_[1,_2]/apertures.yaml"
"patoso/tests/TIC25155310_[1,_2]/candidates.csv"
"patoso/tests/TIC25155310_[1,_2]/lc.csv"
"patoso/tests/TIC25155310_[1,_2]/lc_data.csv"
"patoso/tests/TIC25155310_[1,_2]/params_star.csv"
"patoso/tests/TIC25155310_[1,_2]/properties.yaml"
"patoso/tests/TIC25155310_[1,_2]/transits_stats.csv"
"patoso/tests/TIC25155310_[1,_2]/1/Run_1_PDCSAP-FLUX_TIC25155310_[1, 2].png"
"patoso/tests/TIC25155310_[1,_2]/1/Run_1_ws=0.6048_TIC25155310_[1, 2].png"
"patoso/tests/TIC25155310_[1,_2]/1/Run_1_ws=2.3186_TIC25155310_[1, 2].png"
"patoso/tests/TIC25155310_[1,_2]/1/lc_0.csv"
"patoso/tests/TIC25155310_[1,_2]/1/lc_1.csv"
"patoso/tests/TIC25155310_[1,_2]/1/lc_2.csv"
"patoso/tests/TIC25155310_[1,_2]/2/Run_2_PDCSAP-FLUX_TIC25155310_[1, 2].png"
"patoso/tests/TIC25155310_[1,_2]/2/Run_2_ws=0.6048_TIC25155310_[1, 2].png"
"patoso/tests/TIC25155310_[1,_2]/2/lc_0.csv"
"patoso/tests/TIC25155310_[1,_2]/2/lc_1.csv"
"patoso/tests/TIC25155310_[1,_2]/2/lc_2.csv"
"patoso/tests/TIC25155310_[1,_2]/detrends/Detrends_TIC25155310_[1, 2].png"
"patoso/tests/TIC25155310_[1,_2]/detrends/Detrends_TIC25155310_[1, 2]_time_1325.2980147804474_1381.5147060742997.png"
"patoso/tests/TIC25155310_[1,_2]/rms_mask/High_RMS_Mask_TIC25155310_1.png"
patoso-0.1.1.dist-info/LICENSE
patoso-0.1.1.dist-info/METADATA
patoso-0.1.1.dist-info/WHEEL
patoso-0.1.1.dist-info/top_level.txt
patoso-0.1.1.dist-info/RECORD
