Metadata-Version: 2.1
Name: patoso
Version: 0.1.1
Summary: Photometry Analysis of Transiting Objects from Space Observations
Home-page: https://github.com/PlanetHunters/patoso
Author: M. Dévora-Pajares
Author-email: mdevorapajares@protonmail.com
License: UNKNOWN
Platform: UNKNOWN
Classifier: Programming Language :: Python :: 3
Classifier: License :: OSI Approved :: MIT License
Classifier: Operating System :: OS Independent
Requires-Python: >=3.6.8
Requires-Dist: argparse (==1.4.0)
Requires-Dist: beautifulsoup4 (==4.9.3)
Requires-Dist: configparser (==5.0.1)
Requires-Dist: cython (==0.29.21)
Requires-Dist: extension-helpers (==0.1)
Requires-Dist: imageio (==2.9.0)
Requires-Dist: lcbuilder (==0.7.15)
Requires-Dist: matplotlib (==3.3.4)
Requires-Dist: pyparsing (==2.4.7)
Requires-Dist: pyyaml (==5.4.1)
Requires-Dist: reportlab (==3.5.59)
Requires-Dist: setuptools (>=41.0.0)
